neural_optimiser/__init__.py
neural_optimiser/calculators/__init__.py
neural_optimiser/calculators/_fairchem.py
neural_optimiser/calculators/_mace.py
neural_optimiser/calculators/_mmff94.py
neural_optimiser/calculators/_rand.py
neural_optimiser/calculators/base.py
neural_optimiser/conformers/__init__.py
neural_optimiser/conformers/_conformer.py
neural_optimiser/conformers/_conformer_batch.py
neural_optimiser/datasets/base.py
neural_optimiser/optimisers/__init__.py
neural_optimiser/optimisers/_bfgs.py
neural_optimiser/optimisers/base.py
neural_optimiser-0.0.10.dist-info/licenses/LICENSE
neural_optimiser-0.0.10.dist-info/METADATA
neural_optimiser-0.0.10.dist-info/WHEEL
neural_optimiser-0.0.10.dist-info/top_level.txt
neural_optimiser-0.0.10.dist-info/RECORD
