Metadata-Version: 2.4
Name: neural-optimiser
Version: 0.0.10
Summary: Batched optimisation algorithms for neural network potential driven molecular dynamics.
Author-email: Ewan Wallace <erw@wallace2.com>
License-Expression: Apache-2.0
Project-URL: Homepage, https://github.com/erwallace/neural-optimiser
Requires-Python: ==3.11.*
License-File: LICENSE
Requires-Dist: torch==2.8.0
Requires-Dist: torch-cluster
Requires-Dist: torch-geometric==2.7.0
Requires-Dist: mace-torch
Requires-Dist: cuequivariance_torch
Requires-Dist: rdkit
Requires-Dist: ase
Requires-Dist: numpy
Requires-Dist: loguru
Requires-Dist: universal-pathlib
Provides-Extra: dev
Requires-Dist: pytest; extra == "dev"
Requires-Dist: pre-commit; extra == "dev"
Dynamic: license-file
